server/__init__.py
server/data_server.py
server/test.py
server/test_utils.py
server/logs/__init__.py
server/logs/client_log_config.py
server/logs/decor_log.py
server/logs/server_log_config.py
server/server/__init__.py
server/server/add_user.py
server/server/config_window.py
server/server/core.py
server/server/main_window.py
server/server/remove_user.py
server/server/server_db.py
server/server/stat_window.py
server/utils/__init__.py
server/utils/descriptors.py
server/utils/errors.py
server/utils/login_required.py
server/utils/metaclasses.py
server/utils/utils.py
server_chat_pyqt_still190494-0.1.dist-info/METADATA
server_chat_pyqt_still190494-0.1.dist-info/WHEEL
server_chat_pyqt_still190494-0.1.dist-info/top_level.txt
server_chat_pyqt_still190494-0.1.dist-info/RECORD
